bed_solution_api-0.1.1.dist-info/licenses/LICENSE
internal/__init__.py
internal/_api_config.py
internal/_database.py
internal/_logger.py
internal/_pressure_logger.py
internal/_register_device.py
bed_solution_api-0.1.1.dist-info/METADATA
bed_solution_api-0.1.1.dist-info/WHEEL
bed_solution_api-0.1.1.dist-info/top_level.txt
bed_solution_api-0.1.1.dist-info/RECORD
