Metadata-Version: 2.4
Name: bed-solution-api
Version: 0.1.1
Summary: API for bed solution capston project
Author-email: Jaeho Lee <capstongcp@gmail.com>
License: MIT
Project-URL: Github, https://github.com/iOT-Capston-Design-Project/BedSolution-Python-API
Requires-Python: >=3.9
License-File: LICENSE
Requires-Dist: rich>=13.0
Requires-Dist: supabase>=2.17
Requires-Dist: python-dotenv
Dynamic: license-file
